pyportmgmt/__init__.py
pyportmgmt/capm.py
pyportmgmt/famafrench.py
pyportmgmt/portfolio.py
pyportmgmt-0.0.1.dist-info/METADATA
pyportmgmt-0.0.1.dist-info/WHEEL
pyportmgmt-0.0.1.dist-info/top_level.txt
pyportmgmt-0.0.1.dist-info/RECORD
