Metadata-Version: 2.1
Name: pyportmgmt
Version: 0.0.1
Summary: A package for researchers in the domain Portfolio Management
Home-page: https://github.com/RSB-Balaji/PyPortfolioMgmt
Author: Srinivasa Balaji
Author-email: rsbbalaji19@gmail.com
License: UNKNOWN
Platform: UNKNOWN
Classifier: Programming Language :: Python :: 3
Classifier: License :: OSI Approved :: MIT License
Classifier: Operating System :: OS Independent
Requires-Python: >=3.6
